zip_files/__init__.py
zip_files/backend.py
zip_files/click_extensions.py
zip_files/zip_files.py
zip_files/zip_folder.py
zip_files-0.4.1.dist-info/LICENSE
zip_files-0.4.1.dist-info/METADATA
zip_files-0.4.1.dist-info/WHEEL
zip_files-0.4.1.dist-info/entry_points.txt
zip_files-0.4.1.dist-info/top_level.txt
zip_files-0.4.1.dist-info/RECORD
