Metadata-Version: 2.1
Name: zip_files
Version: 0.4.1
Summary: Command line utilities for creating zip files
Home-page: https://github.com/goerz/zip_files
Author: Michael Goerz
Author-email: mail@michaelgoerz.net
License: BSD license
Keywords: zip
Platform: UNKNOWN
Classifier: Environment :: Console
Classifier: Development Status :: 4 - Beta
Classifier: Intended Audience :: Developers
Classifier: Intended Audience :: System Administrators
Classifier: License :: OSI Approved :: BSD License
Classifier: Topic :: Software Development :: Build Tools
Classifier: Topic :: System :: Archiving :: Compression
Classifier: Topic :: System :: Archiving :: Packaging
Classifier: Topic :: Utilities
Classifier: Natural Language :: English
Classifier: Programming Language :: Python :: 3.6
Classifier: Programming Language :: Python :: 3.7
Classifier: Programming Language :: Python :: 3.8
Classifier: Programming Language :: Python :: 3.9
Classifier: Environment :: Console
Requires-Python: >=3.6
Provides-Extra: dev
